pydabpumps/__init__.py
pydabpumps/api_async.py
pydabpumps/api_sync.py
pydabpumps/const.py
pydabpumps/data.py
pydabpumps-1.2.3.dist-info/licenses/LICENSE
pydabpumps-1.2.3.dist-info/METADATA
pydabpumps-1.2.3.dist-info/WHEEL
pydabpumps-1.2.3.dist-info/top_level.txt
pydabpumps-1.2.3.dist-info/RECORD
